codeinterpreterapi_yayi/__init__.py
codeinterpreterapi_yayi/_patch_parser.py
codeinterpreterapi_yayi/chat_history.py
codeinterpreterapi_yayi/config.py
codeinterpreterapi_yayi/schema.py
codeinterpreterapi_yayi/session.py
codeinterpreterapi_yayi/chains/__init__.py
codeinterpreterapi_yayi/chains/extract_code.py
codeinterpreterapi_yayi/chains/modifications_check.py
codeinterpreterapi_yayi/chains/rm_dl_link.py
codeinterpreterapi_yayi/prompts/__init__.py
codeinterpreterapi_yayi/prompts/modifications_check.py
codeinterpreterapi_yayi/prompts/remove_dl_link.py
codeinterpreterapi_yayi/prompts/system_message.py
codeinterpreterapi_yayi-0.1.15.dist-info/METADATA
codeinterpreterapi_yayi-0.1.15.dist-info/WHEEL
codeinterpreterapi_yayi-0.1.15.dist-info/licenses/LICENSE
codeinterpreterapi_yayi-0.1.15.dist-info/RECORD
