Metadata-Version: 2.3
Name: codeinterpreterapi_yayi
Version: 0.1.15
Summary: CodeInterpreterAPI is an (unofficial) open source python interface for the ChatGPT CodeInterpreter.
Project-URL: Code, https://github.com/AdamZou/codeinterpreter-api.git
Author-email: AdamZou <yz725@cornell.edu>
License: # MIT License
License-File: LICENSE
Keywords: api,chatgpt,codeboxapi,codeinterpreter,codeinterpreterapi,langchain
Classifier: License :: OSI Approved :: MIT License
Classifier: Programming Language :: Python :: 3.9
Classifier: Programming Language :: Python :: 3.10
Classifier: Programming Language :: Python :: 3.11
Classifier: Topic :: Scientific/Engineering :: Artificial Intelligence
Requires-Python: >=3.9.7
Requires-Dist: codeboxapi>=0.0.19
Requires-Dist: langchain
Requires-Dist: openai
Requires-Dist: pip>=24.0
Requires-Dist: pydantic-settings>=2
Requires-Dist: pydantic>=2
Requires-Dist: python-dotenv
Provides-Extra: all
Requires-Dist: jupyter-kernel-gateway; extra == 'all'
Requires-Dist: pillow; extra == 'all'
Requires-Dist: streamlit; extra == 'all'
Provides-Extra: frontend
Requires-Dist: streamlit; extra == 'frontend'
Provides-Extra: image-support
Requires-Dist: pillow; extra == 'image-support'
Provides-Extra: localbox
Requires-Dist: jupyter-kernel-gateway; extra == 'localbox'
